<?xml version = '1.0' encoding = 'UTF-8'?>
<Relation class="oracle.dbtools.crest.model.design.logical.Relation" name="detalle_factura_factura_FK" directorySegmentName="seg_0" id="72E013E8-F7F6-2FAC-45C0-96C047D897B0">
<createdBy>victo</createdBy>
<createdTime>2020-10-17 17:49:27 UTC</createdTime>
<generatorID>F7B8882A-25D6-A67A-93CE-94F0D0009562</generatorID>
<ownerDesignName>modelo datamodeler</ownerDesignName>
<engineerTo>
<item key="F944D07E-8444-C33A-1191-6417613B21FE" value="true"/>
</engineerTo>
<sourcePk>9B67D184-A71D-C01C-A1E6-D8E22C7E5A2C</sourcePk>
<identifying>false</identifying>
<optionalSource>true</optionalSource>
<optionalTarget>false</optionalTarget>
<sourceCardinality>1</sourceCardinality>
<sourceEntity>3B0A043A-924F-6470-341E-0E94C5781398</sourceEntity>
<targetCardinalityString>*</targetCardinalityString>
<targetEntity>0A15B291-9BFB-45F0-F7E1-36DD60B5440D</targetEntity>
<transferable>true</transferable>
<deleteRule>NO ACTION</deleteRule>
</Relation>